net_vis/__init__.py
net_vis/_version.py
net_vis/html_exporter.py
net_vis/models.py
net_vis/netvis.py
net_vis/plotter.py
net_vis/adapters/__init__.py
net_vis/adapters/networkx_adapter.py
net_vis/labextension/package.json
net_vis/labextension/static/509.033ba9040da3c4bbd14d.js
net_vis/labextension/static/634.eec5031aee0f588a473e.js
net_vis/labextension/static/693.411864c65e7065f63ed5.js
net_vis/labextension/static/remoteEntry.5fc008fd415822322709.js
net_vis/labextension/static/style.js
net_vis/labextension/static/third-party-licenses.json
net_vis/nbextension/extension.js
net_vis/resources/netvis-standalone.min.js
net_vis/templates/standalone.html
net_vis/tests/__init__.py
net_vis/tests/conftest.py
net_vis/tests/test_html_exporter.py
net_vis/tests/test_netvis.py
net_vis/tests/test_networkx_adapter.py
net_vis/tests/test_plotter.py
net_vis-0.6.0.data/data/share/jupyter/labextensions/net_vis/package.json
net_vis-0.6.0.data/data/share/jupyter/labextensions/net_vis/static/509.033ba9040da3c4bbd14d.js
net_vis-0.6.0.data/data/share/jupyter/labextensions/net_vis/static/634.eec5031aee0f588a473e.js
net_vis-0.6.0.data/data/share/jupyter/labextensions/net_vis/static/693.411864c65e7065f63ed5.js
net_vis-0.6.0.data/data/share/jupyter/labextensions/net_vis/static/remoteEntry.5fc008fd415822322709.js
net_vis-0.6.0.data/data/share/jupyter/labextensions/net_vis/static/style.js
net_vis-0.6.0.data/data/share/jupyter/labextensions/net_vis/static/third-party-licenses.json
net_vis-0.6.0.data/data/share/jupyter/labextensions/net_vis/install.json
net_vis-0.6.0.dist-info/METADATA
net_vis-0.6.0.dist-info/WHEEL
net_vis-0.6.0.dist-info/licenses/LICENSE
net_vis-0.6.0.dist-info/RECORD
