Metadata-Version: 2.4
Name: net_vis
Version: 0.6.0
Summary: NetVis is a package for interactive visualization of Python NetworkX graphs within JupyterLab. It leverages D3.js for dynamic rendering and provides a high-level Plotter API for effortless network analysis.
Project-URL: Homepage, https://github.com/cmscom/netvis
Project-URL: ChangeLog, https://github.com/cmscom/netvis/blob/main/CHANGES.md
Author-email: Manabu TERADA <terada@cmscom.jp>
License: BSD 3-Clause License
License-File: LICENSE
Keywords: IPython,Jupyter,Widgets
Classifier: Framework :: Jupyter
Classifier: Intended Audience :: Developers
Classifier: Intended Audience :: Science/Research
Classifier: License :: OSI Approved :: BSD License
Classifier: Programming Language :: Python
Classifier: Programming Language :: Python :: 3
Classifier: Programming Language :: Python :: 3.10
Classifier: Programming Language :: Python :: 3.11
Classifier: Programming Language :: Python :: 3.12
Classifier: Programming Language :: Python :: 3.13
Classifier: Programming Language :: Python :: 3.14
Requires-Python: >=3.10
Requires-Dist: networkx>=3.0
Requires-Dist: numpy>=2.0
Provides-Extra: docs
Requires-Dist: jupyter-sphinx; extra == 'docs'
Requires-Dist: nbsphinx; extra == 'docs'
Requires-Dist: nbsphinx-link; extra == 'docs'
Requires-Dist: pypandoc; extra == 'docs'
Requires-Dist: pytest-check-links; extra == 'docs'
Requires-Dist: recommonmark; extra == 'docs'
Requires-Dist: sphinx-rtd-theme; extra == 'docs'
Requires-Dist: sphinx>=1.5; extra == 'docs'
Provides-Extra: examples
Provides-Extra: full
Requires-Dist: scipy>=1.8; extra == 'full'
Provides-Extra: test
Requires-Dist: nbval; extra == 'test'
Requires-Dist: pyright>=1.1.0; extra == 'test'
Requires-Dist: pytest-cov; extra == 'test'
Requires-Dist: pytest>=6.0; extra == 'test'
Requires-Dist: ruff>=0.8.0; extra == 'test'
Requires-Dist: scipy>=1.8; extra == 'test'
